{"status":"done","chunks":{"app":[{"name":"app.js","path":"/Users/fabioandresgarciasanchez/PycharmProjects/intranet_proyectos/static/assets/bundles/deve/app.js"}]},"error":"ModuleBuildError","message":"Module build failed: SyntaxError: Expected corresponding JSX closing tag for <input> (76:24)\n\n  74 |                                 }}/>\n  75 |                             <input type=\"submit\" value=\"Submit\">\n> 76 |                         </form>\n     |                         ^\n  77 |                     </div>\n  78 |                     <div className=\"col-12\">\n  79 |                         <TablaItemsCGUNO mis_permisos={mis_permisos} lista={lista_objetos}/>\n"}